aliyunsdkpolardb/__init__.py
aliyunsdkpolardb/endpoint.py
aliyunsdkpolardb/request/__init__.py
aliyunsdkpolardb/request/v20170801/AbortDBClusterMigrationRequest.py
aliyunsdkpolardb/request/v20170801/AddEncryptionDBRolePrivilegeRequest.py
aliyunsdkpolardb/request/v20170801/AddFirewallRulesRequest.py
aliyunsdkpolardb/request/v20170801/AddSQLRateLimitingRulesRequest.py
aliyunsdkpolardb/request/v20170801/AttachApplicationPolarFSRequest.py
aliyunsdkpolardb/request/v20170801/CancelActiveOperationTasksRequest.py
aliyunsdkpolardb/request/v20170801/CancelCronJobPolicyServerlessRequest.py
aliyunsdkpolardb/request/v20170801/CancelScheduleTasksRequest.py
aliyunsdkpolardb/request/v20170801/CheckAccountNameRequest.py
aliyunsdkpolardb/request/v20170801/CheckAccountNameZonalRequest.py
aliyunsdkpolardb/request/v20170801/CheckConnectionStringRequest.py
aliyunsdkpolardb/request/v20170801/CheckDBNameRequest.py
aliyunsdkpolardb/request/v20170801/CheckDBNameZonalRequest.py
aliyunsdkpolardb/request/v20170801/CheckKMSAuthorizedRequest.py
aliyunsdkpolardb/request/v20170801/CheckServiceLinkedRoleRequest.py
aliyunsdkpolardb/request/v20170801/CloseAITaskRequest.py
aliyunsdkpolardb/request/v20170801/CloseDBClusterMigrationRequest.py
aliyunsdkpolardb/request/v20170801/ContinueDBClusterMigrationRequest.py
aliyunsdkpolardb/request/v20170801/CreateAccountRequest.py
aliyunsdkpolardb/request/v20170801/CreateAccountZonalRequest.py
aliyunsdkpolardb/request/v20170801/CreateActivationCodeRequest.py
aliyunsdkpolardb/request/v20170801/CreateApplicationEndpointAddressRequest.py
aliyunsdkpolardb/request/v20170801/CreateApplicationRequest.py
aliyunsdkpolardb/request/v20170801/CreateBackupRequest.py
aliyunsdkpolardb/request/v20170801/CreateColdStorageInstanceRequest.py
aliyunsdkpolardb/request/v20170801/CreateCronJobPolicyServerlessRequest.py
aliyunsdkpolardb/request/v20170801/CreateDBClusterEndpointRequest.py
aliyunsdkpolardb/request/v20170801/CreateDBClusterEndpointZonalRequest.py
aliyun_python_sdk_polardb-1.8.57.dist-info/LICENSE
aliyun_python_sdk_polardb-1.8.57.dist-info/METADATA
aliyun_python_sdk_polardb-1.8.57.dist-info/WHEEL
aliyun_python_sdk_polardb-1.8.57.dist-info/top_level.txt
aliyun_python_sdk_polardb-1.8.57.dist-info/RECORD
